workbench_tst/__init__.py
workbench_tst/command_line.py
workbench_tst-0.0.3.dist-info/METADATA
workbench_tst-0.0.3.dist-info/WHEEL
workbench_tst-0.0.3.dist-info/entry_points.txt
workbench_tst-0.0.3.dist-info/top_level.txt
workbench_tst-0.0.3.dist-info/RECORD
