Metadata-Version: 2.1
Name: workbench-tst
Version: 0.0.3
Summary: Command-line interface to Workbench's timestamps
Home-page: https://github.com/matthiask/workbench-tst/
Author: Matthias Kestenholz
Author-email: mk@feinheit.ch
License: BSD License
Platform: OS Independent
